{
  "main": {
    "id": "960f1c11311244e3",
    "type": "split",
    "children": [
      {
        "id": "3695b28856622024",
        "type": "tabs",
        "children": [
          {
            "id": "46154ce4c9d8ab2e",
            "type": "leaf",
            "state": {
              "type": "markdown",
              "state": {
                "file": "index.md",
                "mode": "source",
                "source": false
              },
              "icon": "lucide-file",
              "title": "index"
            }
          }
        ]
      }
    ],
    "direction": "vertical"
  },
  "left": {
    "id": "c0ceca18047e75b5",
    "type": "split",
    "children": [
      {
        "id": "4b9cce753cebf60e",
        "type": "tabs",
        "children": [
          {
            "id": "4ddf07855a3830ea",
            "type": "leaf",
            "state": {
              "type": "file-explorer",
              "state": {
                "sortOrder": "alphabetical",
                "autoReveal": false
              },
              "icon": "lucide-folder-closed",
              "title": "파일 탐색기"
            }
          },
          {
            "id": "819af4f14b5b76e4",
            "type": "leaf",
            "state": {
              "type": "search",
              "state": {
                "query": "tag:#DataBase",
                "matchingCase": false,
                "explainSearch": false,
                "collapseAll": false,
                "extraContext": false,
                "sortOrder": "alphabetical"
              },
              "icon": "lucide-search",
              "title": "검색"
            }
          },
          {
            "id": "09ddb180ee81406d",
            "type": "leaf",
            "state": {
              "type": "bookmarks",
              "state": {},
              "icon": "lucide-bookmark",
              "title": "북마크"
            }
          }
        ]
      }
    ],
    "direction": "horizontal",
    "width": 300
  },
  "right": {
    "id": "f9f8508c398bcd94",
    "type": "split",
    "children": [
      {
        "id": "678824eee1352855",
        "type": "tabs",
        "children": [
          {
            "id": "225e76e8871e366c",
            "type": "leaf",
            "state": {
              "type": "backlink",
              "state": {
                "collapseAll": false,
                "extraContext": false,
                "sortOrder": "alphabetical",
                "showSearch": false,
                "searchQuery": "",
                "backlinkCollapsed": false,
                "unlinkedCollapsed": true
              },
              "icon": "links-coming-in",
              "title": "백링크"
            }
          },
          {
            "id": "3062ba4a4c09049c",
            "type": "leaf",
            "state": {
              "type": "outgoing-link",
              "state": {
                "linksCollapsed": false,
                "unlinkedCollapsed": true
              },
              "icon": "links-going-out",
              "title": "나가는 링크"
            }
          },
          {
            "id": "db6d208605a2358b",
            "type": "leaf",
            "state": {
              "type": "tag",
              "state": {
                "sortOrder": "frequency",
                "useHierarchy": true,
                "showSearch": false,
                "searchQuery": ""
              },
              "icon": "lucide-tags",
              "title": "태그"
            }
          },
          {
            "id": "a941719f2632d2fe",
            "type": "leaf",
            "state": {
              "type": "outline",
              "state": {
                "followCursor": false,
                "showSearch": false,
                "searchQuery": ""
              },
              "icon": "lucide-list",
              "title": "개요"
            }
          },
          {
            "id": "2e958c9dd4f388f9",
            "type": "leaf",
            "state": {
              "type": "git-view",
              "state": {},
              "icon": "git-pull-request",
              "title": "Source Control"
            }
          }
        ],
        "currentTab": 4
      }
    ],
    "direction": "horizontal",
    "width": 300
  },
  "left-ribbon": {
    "hiddenItems": {
      "switcher:빠른 전환기 열기": false,
      "graph:그래프 뷰 열기": false,
      "canvas:새 캔버스 만들기": false,
      "daily-notes:오늘의 일일 노트 열기": false,
      "templates:템플릿 삽입": false,
      "command-palette:명령어 팔레트 열기": false,
      "obsidian-git:Open Git source control": false,
      "oz-clear-unused-images:Clear Unused Images": false,
      "webpage-html-export:Export Vault to HTML": false,
      "obsidian-excalidraw-plugin:New drawing": false
    }
  },
  "active": "46154ce4c9d8ab2e",
  "lastOpenFiles": [
    "study/note CI_CD/Obsidian 정적호스팅 CICD 과정.md",
    "study/프로그래밍/Spring.md",
    "study/프로그래밍/Server.md",
    "study/프로그래밍/Obsidian.md",
    "study/프로그래밍/JAVA , OOP.md",
    "study/프로그래밍/DevOps.md",
    "study/프로그래밍/DataBase.md",
    "study/정보처리기사/정보처리기사 필기/필기 5과목 - 정보시스템 구축관리.md",
    "study/정보처리기사/정보처리기사 필기/필기 4과목 - 프로그래밍 언어 활용.md",
    "study/정보처리기사/정보처리기사 필기/필기 3과목 - 데이터베이스 구축.md",
    "study/정보처리기사/정보처리기사 필기/필기 2과목 - 소프트웨어 개발.md",
    "study/정보처리기사/정보처리기사 실기/정보처리 기사 실기 키워드.md",
    "project/hello marketing/유입 통계 APP__SPRING AOP에 관하여.md",
    "project/hello marketing/유입 통계 ADMIN용 테이블 설계 과정.md",
    "project/hello Batch/Spring Batch 트러블 슈팅 부록.md",
    "project/hello Batch/Spring Batch 트러블 슈팅.md",
    "project/hello Batch/Spring Batch 구조 드로잉.md",
    "index.md",
    "사진 및 문서/Pasted image 20250218162355.png",
    "사진 및 문서/Pasted image 20250218162232.png",
    "사진 및 문서/Pasted image 20250218161937.png",
    "사진 및 문서/Pasted image 20250218161847.png",
    "사진 및 문서/Pasted image 20250218161824.png",
    "사진 및 문서/Pasted image 20250218161728.png",
    "사진 및 문서/Pasted image 20250218161515.png",
    "사진 및 문서/Pasted image 20250218161424.png",
    "사진 및 문서/Pasted image 20250218160956.png",
    "사진 및 문서/Pasted image 20250218160532.png",
    "무제.canvas",
    "study/정보처리기사/정보처리기사 필기/필기 1과목 - 소프트웨어 설계.md",
    "study/프로그래밍/etc.md",
    "study/프로그래밍",
    "예치금 배치 리팩토링 구조 드로잉.md",
    "project/hello Batch",
    "사진 및 문서/do-messenger_screenshot_2024-12-30_15_52_09.png.~tmp",
    "study/note CI_CD",
    "project/hello marketing",
    "project",
    "개발 및 공부 히스토리.md",
    "사진 및 문서",
    "공부/정보처리 기사.md",
    "study/정보처리기사/정보처리기사 실기",
    "study/정보처리기사/정보처리기사 필기",
    "study/정보처리기사",
    "환영합니다!.md"
  ]
}